healthsecure/__init__.py
healthsecure/client.py
healthsecure/config.py
healthsecure/exceptions.py
healthsecure/helpers.py
healthsecure/llm_wrapper.py
healthsecure/sdk_helpers.py
healthsecure/types.py
healthsecure/constants/__init__.py
healthsecure/extract/__init__.py
healthsecure/extract/core.py
healthsecure/extract/json_extractor.py
healthsecure/extract/text_extractor.py
healthsecure/extract/v2.py
healthsecure/utils/__init__.py
healthsecure/utils/confidence.py
healthsecure/utils/fingerprint.py
healthsecure-0.3.0.dist-info/METADATA
healthsecure-0.3.0.dist-info/WHEEL
healthsecure-0.3.0.dist-info/top_level.txt
healthsecure-0.3.0.dist-info/RECORD
