Metadata-Version: 2.4
Name: healthsecure
Version: 0.3.0
Summary: Runtime sensitive data exposure detection SDK
Author: Your Org
Keywords: security,data-leakage,privacy,llm,api,sensitive-data,compliance
Classifier: Development Status :: 5 - Production/Stable
Classifier: Intended Audience :: Developers
Classifier: Topic :: Security
Classifier: Topic :: Software Development :: Libraries :: Python Modules
Classifier: Programming Language :: Python :: 3
Classifier: Programming Language :: Python :: 3.9
Classifier: Programming Language :: Python :: 3.10
Classifier: Programming Language :: Python :: 3.11
Classifier: Programming Language :: Python :: 3.12
Classifier: Programming Language :: Python :: 3.13
Requires-Python: >=3.9
Requires-Dist: requests>=2.31.0
Requires-Dist: pydantic>=2.0.0
